{
    "image_name": "2019-12-12T152726.jpg",
    "detections": [
        {
            "bbox": [
                360.6,
                358.3,
                401.24,
                391.54
            ],
            "label": "LABEL_1",
            "score": 0.99
        },
        {
            "bbox": [
                260.77,
                546.55,
                372.91,
                643.74
            ],
            "label": "LABEL_1",
            "score": 0.99
        },
        {
            "bbox": [
                141.15,
                459.46,
                262.15,
                532.82
            ],
            "label": "LABEL_1",
            "score": 0.99
        },
        {
            "bbox": [
                360.05,
                394.12,
                400.62,
                424.43
            ],
            "label": "LABEL_1",
            "score": 0.99
        },
        {
            "bbox": [
                551.3,
                890.11,
                668.63,
                1017.29
            ],
            "label": "LABEL_1",
            "score": 0.98
        },
        {
            "bbox": [
                651.54,
                347.79,
                717.78,
                436.43
            ],
            "label": "LABEL_1",
            "score": 0.95
        },
        {
            "bbox": [
                243.83,
                707.74,
                337.77,
                856.88
            ],
            "label": "LABEL_1",
            "score": 0.91
        },
        {
            "bbox": [
                1.35,
                545.84,
                127.03,
                639.12
            ],
            "label": "LABEL_1",
            "score": 0.99
        },
        {
            "bbox": [
                199.25,
                413.47,
                228.49,
                458.07
            ],
            "label": "LABEL_1",
            "score": 0.61
        },
        {
            "bbox": [
                505.34,
                326.07,
                603.74,
                405.97
            ],
            "label": "LABEL_1",
            "score": 0.98
        },
        {
            "bbox": [
                388.2,
                457.21,
                516.6,
                526.34
            ],
            "label": "LABEL_1",
            "score": 0.98
        },
        {
            "bbox": [
                190.43,
                368.03,
                217.08,
                406.9
            ],
            "label": "LABEL_1",
            "score": 0.89
        },
        {
            "bbox": [
                -0.39,
                914.71,
                112.1,
                1020.25
            ],
            "label": "LABEL_1",
            "score": 0.96
        },
        {
            "bbox": [
                718.05,
                256.93,
                767.33,
                328.17
            ],
            "label": "LABEL_1",
            "score": 0.94
        },
        {
            "bbox": [
                635.12,
                537.92,
                748.22,
                647.67
            ],
            "label": "LABEL_1",
            "score": 0.99
        },
        {
            "bbox": [
                380.77,
                534.42,
                505.94,
                583.11
            ],
            "label": "LABEL_1",
            "score": 0.96
        },
        {
            "bbox": [
                402.81,
                357.2,
                444.24,
                391.18
            ],
            "label": "LABEL_1",
            "score": 0.98
        },
        {
            "bbox": [
                557.71,
                471.13,
                617.37,
                500.34
            ],
            "label": "LABEL_1",
            "score": 0.89
        },
        {
            "bbox": [
                541.88,
                730.17,
                665.24,
                866.29
            ],
            "label": "LABEL_1",
            "score": 0.98
        },
        {
            "bbox": [
                315.98,
                391.36,
                358.06,
                424.7
            ],
            "label": "LABEL_1",
            "score": 1.0
        },
        {
            "bbox": [
                437.99,
                706.45,
                529.44,
                855.03
            ],
            "label": "LABEL_1",
            "score": 1.0
        },
        {
            "bbox": [
                171.42,
                701.9,
                245.56,
                839.13
            ],
            "label": "LABEL_1",
            "score": 0.98
        },
        {
            "bbox": [
                128.38,
                543.55,
                255.94,
                641.94
            ],
            "label": "LABEL_1",
            "score": 0.99
        },
        {
            "bbox": [
                587.26,
                254.86,
                644.54,
                328.29
            ],
            "label": "LABEL_1",
            "score": 0.97
        },
        {
            "bbox": [
                508.94,
                595.82,
                622.62,
                643.67
            ],
            "label": "LABEL_1",
            "score": 0.99
        },
        {
            "bbox": [
                418.47,
                919.46,
                539.77,
                1023.11
            ],
            "label": "LABEL_1",
            "score": 0.96
        },
        {
            "bbox": [
                508.37,
                537.45,
                624.41,
                598.33
            ],
            "label": "LABEL_1",
            "score": 0.99
        },
        {
            "bbox": [
                -0.39,
                914.81,
                106.93,
                1019.31
            ],
            "label": "LABEL_1",
            "score": 0.96
        },
        {
            "bbox": [
                672.63,
                724.34,
                766.65,
                862.39
            ],
            "label": "LABEL_1",
            "score": 0.99
        },
        {
            "bbox": [
                162.26,
                424.92,
                199.05,
                457.58
            ],
            "label": "LABEL_1",
            "score": 0.84
        },
        {
            "bbox": [
                172.13,
                372.54,
                191.49,
                408.78
            ],
            "label": "LABEL_1",
            "score": 0.76
        },
        {
            "bbox": [
                446.54,
                359.92,
                493.34,
                391.69
            ],
            "label": "LABEL_1",
            "score": 0.99
        },
        {
            "bbox": [
                108.8,
                714.15,
                144.71,
                812.55
            ],
            "label": "LABEL_1",
            "score": 0.85
        },
        {
            "bbox": [
                539.05,
                728.63,
                663.68,
                857.72
            ],
            "label": "LABEL_1",
            "score": 1.0
        },
        {
            "bbox": [
                543.85,
                747.49,
                665.39,
                862.74
            ],
            "label": "LABEL_1",
            "score": 1.0
        },
        {
            "bbox": [
                276.17,
                929.46,
                411.98,
                1024.2
            ],
            "label": "LABEL_1",
            "score": 0.96
        },
        {
            "bbox": [
                0.87,
                733.29,
                105.52,
                855.27
            ],
            "label": "LABEL_1",
            "score": 0.99
        },
        {
            "bbox": [
                89.41,
                386.87,
                128.48,
                418.47
            ],
            "label": "LABEL_1",
            "score": 0.97
        },
        {
            "bbox": [
                546.48,
                426.43,
                604.19,
                455.33
            ],
            "label": "LABEL_1",
            "score": 0.7
        },
        {
            "bbox": [
                0.59,
                428.71,
                137.58,
                533.61
            ],
            "label": "LABEL_1",
            "score": 0.99
        },
        {
            "bbox": [
                402.57,
                393.0,
                444.36,
                423.03
            ],
            "label": "LABEL_1",
            "score": 0.99
        },
        {
            "bbox": [
                224.89,
                355.08,
                264.82,
                415.99
            ],
            "label": "LABEL_1",
            "score": 0.99
        },
        {
            "bbox": [
                246.87,
                709.66,
                340.35,
                854.79
            ],
            "label": "LABEL_1",
            "score": 0.98
        },
        {
            "bbox": [
                340.29,
                704.63,
                435.54,
                856.39
            ],
            "label": "LABEL_1",
            "score": 0.99
        },
        {
            "bbox": [
                507.99,
                538.04,
                624.78,
                598.73
            ],
            "label": "LABEL_1",
            "score": 0.98
        },
        {
            "bbox": [
                446.29,
                392.03,
                493.65,
                422.95
            ],
            "label": "LABEL_1",
            "score": 0.99
        },
        {
            "bbox": [
                0.73,
                545.68,
                129.96,
                640.91
            ],
            "label": "LABEL_1",
            "score": 0.79
        },
        {
            "bbox": [
                493.79,
                244.07,
                563.51,
                315.03
            ],
            "label": "LABEL_1",
            "score": 0.97
        },
        {
            "bbox": [
                316.79,
                357.99,
                358.43,
                388.59
            ],
            "label": "LABEL_1",
            "score": 0.99
        },
        {
            "bbox": [
                121.85,
                921.93,
                257.4,
                1021.86
            ],
            "label": "LABEL_1",
            "score": 0.96
        },
        {
            "bbox": [
                127.15,
                378.53,
                150.37,
                413.59
            ],
            "label": "LABEL_1",
            "score": 0.71
        },
        {
            "bbox": [
                262.45,
                462.21,
                386.18,
                538.34
            ],
            "label": "LABEL_1",
            "score": 0.99
        },
        {
            "bbox": [
                2.06,
                544.64,
                125.85,
                638.52
            ],
            "label": "LABEL_1",
            "score": 0.98
        },
        {
            "bbox": [
                505.39,
                325.85,
                604.46,
                405.36
            ],
            "label": "LABEL_1",
            "score": 0.98
        },
        {
            "bbox": [
                271.35,
                356.32,
                315.14,
                386.17
            ],
            "label": "LABEL_1",
            "score": 0.99
        },
        {
            "bbox": [
                653.96,
                260.54,
                711.76,
                335.83
            ],
            "label": "LABEL_1",
            "score": 0.99
        },
        {
            "bbox": [
                272.24,
                391.79,
                317.06,
                422.45
            ],
            "label": "LABEL_1",
            "score": 0.99
        },
        {
            "bbox": [
                669.15,
                720.08,
                767.78,
                801.36
            ],
            "label": "LABEL_1",
            "score": 0.99
        },
        {
            "bbox": [
                677.62,
                956.11,
                766.99,
                1024.11
            ],
            "label": "LABEL_1",
            "score": 0.74
        },
        {
            "bbox": [
                382.23,
                575.11,
                500.35,
                645.41
            ],
            "label": "LABEL_1",
            "score": 0.99
        }
    ]
}